entity_emailer/__init__.py
entity_emailer/apps.py
entity_emailer/interface.py
entity_emailer/models.py
entity_emailer/signals.py
entity_emailer/urls.py
entity_emailer/utils.py
entity_emailer/version.py
entity_emailer/views.py
entity_emailer/management/__init__.py
entity_emailer/management/commands/__init__.py
entity_emailer/management/commands/add_email_medium.py
entity_emailer/management/commands/entity_emailer_admin_setup.py
entity_emailer/migrations/0001_0004_squashed.py
entity_emailer/migrations/__init__.py
entity_emailer/tests/__init__.py
entity_emailer/tests/interface_tests.py
entity_emailer/tests/test_management_command.py
entity_emailer/tests/test_models.py
entity_emailer/tests/test_views.py
entity_emailer/tests/utils.py
entity_emailer/tests/utils_tests.py
django_entity_emailer-2.2.0.dist-info/LICENSE
django_entity_emailer-2.2.0.dist-info/METADATA
django_entity_emailer-2.2.0.dist-info/WHEEL
django_entity_emailer-2.2.0.dist-info/top_level.txt
django_entity_emailer-2.2.0.dist-info/RECORD
