Metadata-Version: 2.1
Name: django-entity-emailer
Version: 2.2.0
Summary: Make emailing users easy and entity-based.
Home-page: https://github.com/ambitioninc/django-entity-emailer
Author: Erik Swanson
Author-email: opensource@ambition.com
License: MIT
Classifier: Programming Language :: Python
Classifier: Programming Language :: Python :: 3.7
Classifier: Programming Language :: Python :: 3.8
Classifier: Programming Language :: Python :: 3.9
Classifier: Intended Audience :: Developers
Classifier: License :: OSI Approved :: MIT License
Classifier: Operating System :: OS Independent
Classifier: Framework :: Django
Classifier: Framework :: Django :: 3.2
Classifier: Framework :: Django :: 4.0
Classifier: Framework :: Django :: 4.1
Classifier: Framework :: Django :: 4.2
License-File: LICENSE
Requires-Dist: Django (>=3.2)
Requires-Dist: django-db-mutex (>=3.1.0)
Requires-Dist: django-entity (>=6.1.0)
Requires-Dist: django-entity-event (>=3.1.0)
Requires-Dist: ambition-utils (>=3.1.6)
Requires-Dist: beautifulsoup4 (>=4.3.2)
